{
    "os": "Linux-5.4.0-58-generic-x86_64-with-glibc2.29",
    "python": "3.8.5",
    "heartbeatAt": "2020-12-24T13:13:32.179102",
    "startedAt": "2020-12-24T13:13:30.834893",
    "docker": null,
    "gpu": "GeForce RTX 2060 SUPER",
    "gpu_count": 1,
    "cpu_count": 12,
    "cuda": "10.1.243",
    "args": [
        "--config",
        "configs/learned_2d.yaml"
    ],
    "state": "running",
    "codePath": "code/main.py",
    "program": "main.py",
    "git": {
        "remote": "https://github.com/NishantPrabhu/Self-Attention-and-Convolutions",
        "commit": "ddf08e39306f5b259f36acdf6f3433e152d633dc"
    },
    "email": "me17b084@smail.iitm.ac.in",
    "root": "/home/nishant/Desktop/Desktop/Papers2code/Implementations/Self-Attention-and-Convolutions",
    "host": "nishant-aorus",
    "username": "nishant",
    "executable": "/usr/bin/python3"
}
